{"about":"I'm Santiago Rodriguez from Colombia, and I do content Development. I really enjoy languages and frameworks like Python Native, as well as work in WordPress. I also enjoy wireframing, ui, ux, and design in general. You can check out my Linkedln at https://www.linkedin.com/in/santiago-esteban-rodr%C3%ADguez-guti%C3%A9rrez-723106225 .","calendar":{"1688429903":1},"completedChallenges":[],"isApisMicroservicesCert":false,"isBackEndCert":false,"isCheater":false,"isDonating":false,"is2018DataVisCert":false,"isDataVisCert":false,"isFrontEndCert":false,"isFullStackCert":false,"isFrontEndLibsCert":false,"isHonest":true,"isInfosecQaCert":false,"isQaCertV7":false,"isInfosecCertV7":false,"isJsAlgoDataStructCert":false,"isRelationalDatabaseCertV8":false,"isRespWebDesignCert":false,"isSciCompPyCertV7":false,"isDataAnalysisPyCertV7":false,"isMachineLearningPyCertV7":false,"isCollegeAlgebraPyCertV8":false,"location":"Colombia","name":"Santiago Rodriguez ","partiallyCompletedChallenges":[],"points":1,"portfolio":[],"profileUI":{"isLocked":true,"showAbout":false,"showCerts":false,"showDonation":false,"showHeatMap":false,"showLocation":false,"showName":false,"showPoints":false,"showPortfolio":false,"showTimeLine":false},"savedChallenges":[],"username":"santimars","yearsTopContributor":[],"currentChallengeId":"","email":"santiagoestebanrodriguezgutier@gmail.com","emailVerified":true,"id":"64a3654f4c1386048e4361be","sendQuincyEmail":false,"theme":"night","sound":false,"keyboardShortcuts":false,"completedChallengeCount":0,"acceptedPrivacyTerms":false,"isEmailVerified":true,"picture":"https://media.licdn.com/dms/image/C4E03AQH8OucKfj34Iw/profile-displayphoto-shrink_400_400/0/1636036619736?e=1694044800&v=beta&t=6MIVwVYd7FipmHPZ42PGxUh0A6Bsd36FmPv7hR5rFdg","joinDate":"2023-07-04T00:18:23.000Z","sessionUser":true}